Examples/__init__.py
RSTAB/__init__.py
RSTAB/baseData.py
RSTAB/baseSettings.py
RSTAB/connectionGlobals.py
RSTAB/dataTypes.py
RSTAB/dependencies.py
RSTAB/enums.py
RSTAB/formula.py
RSTAB/globalParameter.py
RSTAB/initModel.py
RSTAB/suds_requests.py
RSTAB/AluminumDesign/__init__.py
RSTAB/AluminumDesign/aluminumSLSConfiguration.py
RSTAB/AluminumDesign/aluminumULSConfiguration.py
RSTAB/BasicObjects/__init__.py
RSTAB/BasicObjects/material.py
RSTAB/BasicObjects/member.py
RSTAB/BasicObjects/memberSet.py
RSTAB/BasicObjects/node.py
RSTAB/BasicObjects/section.py
RSTAB/Calculate/__init__.py
RSTAB/Calculate/optimizationSettings.py
RSTAB/ConcreteDesign/ConcreteServiceabilityConfigurations.py
RSTAB/ConcreteDesign/ConcreteUltimateConfigurations.py
RSTAB/ConcreteDesign/__init__.py
RSTAB/DynamicLoads/__init__.py
RSTAB/DynamicLoads/responseSpectrum.py
RSTAB/GuideObjects/__init__.py
RSTAB/GuideObjects/coordinateSystem.py
RSTAB/GuideObjects/note.py
RSTAB/Imperfections/__init__.py
RSTAB/Imperfections/imperfectionCase.py
RSTAB/Imperfections/memberImperfection.py
RSTAB/Imperfections/membersetImperfection.py
RSTAB/ImportExport/__init__.py
RSTAB/ImportExport/exports.py
RSTAB/ImportExport/imports.py
RSTAB/LoadCasesAndCombinations/__init__.py
RSTAB/LoadCasesAndCombinations/action.py
RSTAB/LoadCasesAndCombinations/actionCombination.py
RSTAB/LoadCasesAndCombinations/combinationWizard.py
RSTAB/LoadCasesAndCombinations/designSituation.py
RSTAB/LoadCasesAndCombinations/loadCase.py
RSTAB/LoadCasesAndCombinations/loadCasesAndCombinations.py
RSTAB/LoadCasesAndCombinations/loadCombination.py
RSTAB/LoadCasesAndCombinations/modalAnalysisSettings.py
RSTAB/LoadCasesAndCombinations/resultCombination.py
RSTAB/LoadCasesAndCombinations/spectralAnalysisSettings.py
RSTAB/LoadCasesAndCombinations/stabilityAnalysisSettings.py
RSTAB/LoadCasesAndCombinations/staticAnalysisSettings.py
RSTAB/Loads/__init__.py
RSTAB/Loads/imposedNodalDeformation.py
RSTAB/Loads/memberLoad.py
RSTAB/Loads/membersetload.py
rstab-1.10.3.dist-info/licenses/LICENSE
rstab-1.10.3.dist-info/METADATA
rstab-1.10.3.dist-info/WHEEL
rstab-1.10.3.dist-info/top_level.txt
rstab-1.10.3.dist-info/RECORD
