Metadata-Version: 2.4
Name: RSTAB
Version: 1.10.3
Summary: Python Framework for RSTAB9 Web Services
Home-page: https://github.com/Dlubal-Software/RSTAB_Python_Client
Author: Dlubal Software
Author-email: info@dlubal.com
License: MIT
Classifier: License :: OSI Approved :: MIT License
Classifier: Programming Language :: Python :: 3
Classifier: Programming Language :: Python :: 3.10
Classifier: Programming Language :: Python :: 3.11
License-File: LICENSE
Requires-Dist: requests
Requires-Dist: six
Requires-Dist: suds-py3
Requires-Dist: xmltodict
Requires-Dist: pytest
Requires-Dist: psutil
Requires-Dist: mock
Requires-Dist: setuptools
Dynamic: author
Dynamic: author-email
Dynamic: classifier
Dynamic: description
Dynamic: description-content-type
Dynamic: home-page
Dynamic: license
Dynamic: license-file
Dynamic: requires-dist
Dynamic: summary
